cgsensor/__init__.py
cgsensor/bme280.py
cgsensor/cli.py
cgsensor/scd41.py
cgsensor/tsl2572.py
cgsensor-1.2.dist-info/licenses/LICENSE
cgsensor-1.2.dist-info/METADATA
cgsensor-1.2.dist-info/WHEEL
cgsensor-1.2.dist-info/entry_points.txt
cgsensor-1.2.dist-info/top_level.txt
cgsensor-1.2.dist-info/RECORD
