Metadata-Version: 2.4
Name: cgsensor
Version: 1.2
Summary: Python package and command line tool to control sensors on Raspberry Pi
Home-page: https://github.com/IndoorCorgi/cgsensor
Author: Indoor Corgi
Author-email: indoorcorgi@gmail.com
License: Apache License 2.0
Requires-Python: >=3.6
License-File: LICENSE
Requires-Dist: docopt
Requires-Dist: smbus2
Dynamic: author
Dynamic: author-email
Dynamic: home-page
Dynamic: license
Dynamic: license-file
Dynamic: requires-dist
Dynamic: requires-python
Dynamic: summary
